bsci/__init__.py
bsci/bootstrapped_confidence_intervals.py
bsci-1.1.dist-info/LICENSE.txt
bsci-1.1.dist-info/METADATA
bsci-1.1.dist-info/WHEEL
bsci-1.1.dist-info/top_level.txt
bsci-1.1.dist-info/zip-safe
bsci-1.1.dist-info/RECORD
