Metadata-Version: 2.1
Name: bsci
Version: 1.1
Summary: Constructing frequentist confidence intervals using the statistical bootstrap
Home-page: https://github.com/famura/bsci
Author: Fabio Muratore
Author-email: fabio.muratore@famura.net
License: UNKNOWN
Project-URL: Source, https://github.com/famura/bsci
Project-URL: Bug Reports, https://github.com/famura/bsci/issues
Keywords: statistical bootstrap,the bootstrap,confidence interval
Platform: UNKNOWN
Classifier: License :: OSI Approved :: MIT License
Classifier: Development Status :: 5 - Production/Stable
Classifier: Operating System :: OS Independent
Classifier: Programming Language :: Python :: 3.8
Classifier: Programming Language :: Python :: 3.7
Classifier: Programming Language :: Python :: 3 :: Only
Requires-Python: >=3.7, <4
Requires-Dist: numpy
Provides-Extra: dev
Requires-Dist: black ; extra == 'dev'
Requires-Dist: isort ; extra == 'dev'
Requires-Dist: matplotlib ; extra == 'dev'
Requires-Dist: pytest ; extra == 'dev'
Requires-Dist: pytest-cov ; extra == 'dev'
Requires-Dist: scipy ; extra == 'dev'
